{
  "annotations": {
    "list": [
      {"builtIn": 1, "datasource": "-- Grafana --", "enable": true, "hide": true,
       "iconColor": "rgba(0, 211, 255, 1)", "name": "Annotations & Alerts", "type": "dashboard"}
    ]
  },
  "editable": true,
  "gnetId": null,
  "graphTooltip": 0,
  "id": null,
  "links": [],
  "panels": [
    {
      "aliasColors": {},
      "bars": false,
      "dashLength": 10,
      "dashes": false,
      "datasource": null,
      "fieldConfig": {"defaults": {}},
      "fill": 1,
      "fillGradient": 0,
      "gridPos": {"h": 8, "w": 12, "x": 0, "y": 0},
      "hiddenSeries": false,
      "id": 2,
      "legend": {"avg": false, "current": false, "max": false, "min": false, "show": true, "total": false, "values": false},
      "lines": true,
      "linewidth": 1,
      "nullPointMode": "null",
      "options": {"alertThreshold": true},
      "percentage": false,
      "pluginVersion": "8.0.0",
      "pointradius": 2,
      "points": false,
      "renderer": "flot",
      "seriesOverrides": [],
      "spaceLength": 10,
      "stack": false,
      "steppedLine": false,
      "targets": [
        {"expr": "rate(amj_chat_requests_total{status=\"success\"}[5m])", "legendFormat": "Success", "refId": "A"},
        {"expr": "rate(amj_chat_requests_total{status=\"error\"}[5m])", "legendFormat": "Errors", "refId": "B"}
      ],
      "thresholds": [],
      "timeFrom": null,
      "timeRegions": [],
      "timeShift": null,
      "title": "Chat Request Rate (QPS)",
      "tooltip": {"shared": true, "sort": 0, "value_type": "individual"},
      "type": "graph",
      "xaxis": {"buckets": null, "mode": "time", "name": null, "show": true, "values": []},
      "yaxes": [{"format": "short", "label": null, "logBase": 1, "max": null, "min": "0", "show": true}]
    },
    {
      "datasource": null,
      "fieldConfig": {"defaults": {}},
      "gridPos": {"h": 8, "w": 12, "x": 12, "y": 0},
      "id": 4,
      "options": {"orientation": "auto", "reduceOptions": {"calcs": ["lastNotNull"], "fields": "", "values": false},
                 "showThresholdLabels": false, "showThresholdMarkers": true},
      "pluginVersion": "8.0.0",
      "targets": [
        {"expr": "rate(amj_tool_executions_total[5m])", "legendFormat": "{{tool}}", "refId": "A"}
      ],
      "title": "Tool Executions / sec",
      "type": "bargauge"
    },
    {
      "aliasColors": {},
      "bars": false,
      "dashLength": 10,
      "dashes": false,
      "datasource": null,
      "fieldConfig": {"defaults": {}},
      "fill": 1,
      "fillGradient": 0,
      "gridPos": {"h": 8, "w": 8, "x": 0, "y": 8},
      "hiddenSeries": false,
      "id": 6,
      "legend": {"avg": false, "current": false, "max": false, "min": false, "show": true, "total": false, "values": false},
      "lines": true,
      "linewidth": 1,
      "nullPointMode": "null",
      "options": {"alertThreshold": true},
      "percentage": false,
      "pluginVersion": "8.0.0",
      "pointradius": 2,
      "points": false,
      "renderer": "flot",
      "seriesOverrides": [],
      "spaceLength": 10,
      "stack": false,
      "steppedLine": false,
      "targets": [
        {"expr": "histogram_quantile(0.50, rate(amj_chat_duration_seconds_bucket[5m]))", "legendFormat": "p50", "refId": "A"},
        {"expr": "histogram_quantile(0.95, rate(amj_chat_duration_seconds_bucket[5m]))", "legendFormat": "p95", "refId": "B"},
        {"expr": "histogram_quantile(0.99, rate(amj_chat_duration_seconds_bucket[5m]))", "legendFormat": "p99", "refId": "C"}
      ],
      "thresholds": [],
      "timeFrom": null,
      "timeRegions": [],
      "timeShift": null,
      "title": "Latency (p50/p95/p99)",
      "tooltip": {"shared": true, "sort": 0, "value_type": "individual"},
      "type": "graph",
      "xaxis": {"buckets": null, "mode": "time", "name": null, "show": true, "values": []},
      "yaxes": [{"format": "s", "label": null, "logBase": 1, "max": null, "min": "0", "show": true}]
    },
    {
      "datasource": null,
      "fieldConfig": {"defaults": {}},
      "gridPos": {"h": 8, "w": 8, "x": 8, "y": 8},
      "id": 8,
      "options": {"colorMode": "value", "graphMode": "area", "justifyMode": "auto",
                  "orientation": "auto", "reduceOptions": {"calcs": ["lastNotNull"], "fields": "", "values": false},
                  "textMode": "auto"},
      "pluginVersion": "8.0.0",
      "targets": [
        {"expr": "rate(amj_model_cache_hits_total[5m]) / (rate(amj_model_cache_hits_total[5m]) + rate(amj_model_cache_misses_total[5m]) + 0.001)", "legendFormat": "Hit Rate", "refId": "A"}
      ],
      "title": "Cache Hit Rate",
      "type": "stat"
    },
    {
      "datasource": null,
      "fieldConfig": {"defaults": {}},
      "gridPos": {"h": 8, "w": 8, "x": 16, "y": 8},
      "id": 10,
      "options": {"orientation": "auto", "reduceOptions": {"calcs": ["lastNotNull"], "fields": "", "values": false},
                  "showThresholdLabels": false, "showThresholdMarkers": true},
      "pluginVersion": "8.0.0",
      "targets": [
        {"expr": "rate(amj_prompt_guard_blocks_total[5m])", "legendFormat": "{{category}}", "refId": "A"}
      ],
      "title": "Prompt Guard Blocks / sec",
      "type": "bargauge"
    },
    {
      "aliasColors": {},
      "bars": false,
      "dashLength": 10,
      "dashes": false,
      "datasource": null,
      "fieldConfig": {"defaults": {}},
      "fill": 1,
      "fillGradient": 0,
      "gridPos": {"h": 8, "w": 12, "x": 0, "y": 16},
      "hiddenSeries": false,
      "id": 12,
      "legend": {"avg": false, "current": false, "max": false, "min": false, "show": true, "total": false, "values": false},
      "lines": true,
      "linewidth": 1,
      "nullPointMode": "null",
      "options": {"alertThreshold": true},
      "percentage": false,
      "pluginVersion": "8.0.0",
      "pointradius": 2,
      "points": false,
      "renderer": "flot",
      "targets": [
        {"expr": "amj_active_sessions", "legendFormat": "Active Sessions", "refId": "A"}
      ],
      "thresholds": [],
      "timeFrom": null,
      "timeRegions": [],
      "timeShift": null,
      "title": "Active SSE Sessions",
      "type": "graph"
    },
    {
      "aliasColors": {},
      "bars": false,
      "dashLength": 10,
      "dashes": false,
      "datasource": null,
      "fieldConfig": {"defaults": {}},
      "fill": 1,
      "fillGradient": 0,
      "gridPos": {"h": 8, "w": 12, "x": 12, "y": 16},
      "hiddenSeries": false,
      "id": 14,
      "legend": {"avg": false, "current": false, "max": false, "min": false, "show": true, "total": false, "values": false},
      "lines": true,
      "linewidth": 1,
      "nullPointMode": "null",
      "options": {"alertThreshold": true},
      "percentage": false,
      "pluginVersion": "8.0.0",
      "pointradius": 2,
      "points": false,
      "renderer": "flot",
      "targets": [
        {"expr": "rate(amj_sandbox_blocks_total[5m])", "legendFormat": "{{reason}}", "refId": "A"}
      ],
      "thresholds": [],
      "timeFrom": null,
      "timeRegions": [],
      "timeShift": null,
      "title": "Sandbox Blocks / sec",
      "type": "graph"
    }
  ],
  "refresh": "30s",
  "schemaVersion": 27,
  "style": "dark",
  "tags": ["aimodeljudge", "security"],
  "templating": {"list": []},
  "time": {"from": "now-1h", "to": "now"},
  "timepicker": {},
  "timezone": "",
  "title": "AIModelJudge — Dashboard",
  "uid": "amj-main",
  "version": 1
}
